<?xml version="1.0" encoding="utf-8"?>
<Deployment xmlns="http://schemas.microsoft.com/windowsphone/2009/deployment" AppPlatformVersion="7.1">
  <App xmlns="" ProductID="{efc64ada-fb91-4665-81ce-944a506eca5b}" Title="AR Drone Remote" RuntimeType="Silverlight" Version="1.0.0.0" Genre="apps.normal" Author="Thomas Adams" Description="Remote Control for Parrot Brand AR Drone 2.0" Publisher="Thomas Adams" BitsPerPixel="32">
    <IconPath IsRelative="true" IsResource="false">Assets\AppIcon.png</IconPath>
    <Capabilities>
      <Capability Name="ID_CAP_NETWORKING" />
      <Capability Name="ID_CAP_SENSORS" />
      <Capability Name="ID_CAP_WEBBROWSERCOMPONENT" />
    </Capabilities>
    <Tasks>
      <DefaultTask Name="_default" NavigationPage="MainPage.xaml" />
    </Tasks>
    <Tokens>
      <PrimaryToken TokenID="AR_Drone_Remote_for_Windows_Phone_7Token" TaskName="_default">
        <TemplateType5>
          <BackgroundImageURI IsRelative="true" IsResource="false">Assets\AppTileMedium.png</BackgroundImageURI>
          <Count>0</Count>
          <Title>AR Drone Remote</Title>
        </TemplateType5>
      </PrimaryToken>
    </Tokens>
  </App>
</Deployment>